swifr_pkg/SWIFr.py
swifr_pkg/SWIFr_train.py
swifr_pkg/__init__.py
swifr_pkg/calibration.py
swifr_pkg/requirements.txt
swifr-2.2.2.dist-info/LICENSE
swifr-2.2.2.dist-info/METADATA
swifr-2.2.2.dist-info/WHEEL
swifr-2.2.2.dist-info/entry_points.txt
swifr-2.2.2.dist-info/RECORD
