Metadata-Version: 2.1
Name: swifr
Version: 2.2.2
Summary: SWIF(r) - SWeep Inference Framework(controlling for correlation) - package for detecting adaptation in population data
Home-page: https://github.com/ramachandran-lab/SWIFr
License: GPL-3.0
Keywords: genomics,population genetics,adaptation
Author: Lauren Alpert Sugden
Author-email: lauren.v.sugden@gmail.com
Requires-Python: >=3.10,<4.0
Classifier: License :: OSI Approved :: GNU General Public License v3 (GPLv3)
Classifier: Programming Language :: Python :: 3
Classifier: Programming Language :: Python :: 3.10
Classifier: Programming Language :: Python :: 3.11
Classifier: Programming Language :: Python :: 3.12
Requires-Dist: cycler (>=0.12.1,<0.13.0)
Requires-Dist: future (>=1.0.0,<2.0.0)
Requires-Dist: matplotlib (>=3.9.1,<4.0.0)
Requires-Dist: numpy (==1.26.4)
Requires-Dist: pyparsing (==2.4.2)
Requires-Dist: python-dateutil (>=2.9.0.post0,<3.0.0)
Requires-Dist: scikit-learn (>=1.5.0,<2.0.0)
Requires-Dist: scipy (>=1.14.0,<2.0.0)
Requires-Dist: six (>=1.16.0,<2.0.0)
